{
  "urlPatterns": [
    {
      "id": "1558106",
      "url": "https://uurl.kbr.be/1558106",
      "pattern": {
        "id": "1558106",
        "hierarchicalPath": [
          {
            "strategy": "direct_digits",
            "path": "1/5/5/8/1/0/6"
          },
          {
            "strategy": "with_prefix",
            "path": "A/1/5/5/8/1/0/6"
          },
          {
            "strategy": "nested_structure",
            "path": "15/58/10/6"
          }
        ],
        "possibleTileStructure": {
          "possibleZoomLevels": {
            "min": 0,
            "max": 10,
            "common": [
              0,
              1,
              2,
              3,
              4,
              5,
              6,
              7,
              8,
              9,
              10
            ],
            "description": "XLimage uses pyramid structure with multiple resolution levels"
          },
          "tileSize": {
            "common": [
              256,
              512,
              1024
            ],
            "default": 256,
            "description": "Most tile systems use 256x256 or 512x512 tiles"
          },
          "fileFormat": {
            "likely": [
              "jpg",
              "jpeg",
              "png"
            ],
            "xlimage_specific": "XLimage may use proprietary format or standard JPEG",
            "quality": "High quality for manuscript viewing"
          },
          "namingConvention": [
            {
              "pattern": "BE-KBR00_A_1558106_0000_00_00_0001.jpg",
              "description": "Standard KBR naming convention"
            },
            {
              "pattern": "{zoom_level}_{tile_x}_{tile_y}.jpg",
              "description": "Common tile naming"
            },
            {
              "pattern": "{id}_{zoom}_{x}_{y}.{format}",
              "description": "ID-based tile naming"
            }
          ]
        }
      }
    },
    {
      "id": "1496332",
      "url": "https://uurl.kbr.be/1496332",
      "pattern": {
        "id": "1496332",
        "hierarchicalPath": [
          {
            "strategy": "direct_digits",
            "path": "1/4/9/6/3/3/2"
          },
          {
            "strategy": "with_prefix",
            "path": "A/1/4/9/6/3/3/2"
          },
          {
            "strategy": "nested_structure",
            "path": "14/96/33/2"
          }
        ],
        "possibleTileStructure": {
          "possibleZoomLevels": {
            "min": 0,
            "max": 10,
            "common": [
              0,
              1,
              2,
              3,
              4,
              5,
              6,
              7,
              8,
              9,
              10
            ],
            "description": "XLimage uses pyramid structure with multiple resolution levels"
          },
          "tileSize": {
            "common": [
              256,
              512,
              1024
            ],
            "default": 256,
            "description": "Most tile systems use 256x256 or 512x512 tiles"
          },
          "fileFormat": {
            "likely": [
              "jpg",
              "jpeg",
              "png"
            ],
            "xlimage_specific": "XLimage may use proprietary format or standard JPEG",
            "quality": "High quality for manuscript viewing"
          },
          "namingConvention": [
            {
              "pattern": "BE-KBR00_A_1496332_0000_00_00_0001.jpg",
              "description": "Standard KBR naming convention"
            },
            {
              "pattern": "{zoom_level}_{tile_x}_{tile_y}.jpg",
              "description": "Common tile naming"
            },
            {
              "pattern": "{id}_{zoom}_{x}_{y}.{format}",
              "description": "ID-based tile naming"
            }
          ]
        }
      }
    },
    {
      "id": "1040094",
      "url": "https://uurl.kbr.be/1040094",
      "pattern": {
        "id": "1040094",
        "hierarchicalPath": [
          {
            "strategy": "direct_digits",
            "path": "1/0/4/0/0/9/4"
          },
          {
            "strategy": "with_prefix",
            "path": "A/1/0/4/0/0/9/4"
          },
          {
            "strategy": "nested_structure",
            "path": "10/40/09/4"
          }
        ],
        "possibleTileStructure": {
          "possibleZoomLevels": {
            "min": 0,
            "max": 10,
            "common": [
              0,
              1,
              2,
              3,
              4,
              5,
              6,
              7,
              8,
              9,
              10
            ],
            "description": "XLimage uses pyramid structure with multiple resolution levels"
          },
          "tileSize": {
            "common": [
              256,
              512,
              1024
            ],
            "default": 256,
            "description": "Most tile systems use 256x256 or 512x512 tiles"
          },
          "fileFormat": {
            "likely": [
              "jpg",
              "jpeg",
              "png"
            ],
            "xlimage_specific": "XLimage may use proprietary format or standard JPEG",
            "quality": "High quality for manuscript viewing"
          },
          "namingConvention": [
            {
              "pattern": "BE-KBR00_A_1040094_0000_00_00_0001.jpg",
              "description": "Standard KBR naming convention"
            },
            {
              "pattern": "{zoom_level}_{tile_x}_{tile_y}.jpg",
              "description": "Common tile naming"
            },
            {
              "pattern": "{id}_{zoom}_{x}_{y}.{format}",
              "description": "ID-based tile naming"
            }
          ]
        }
      }
    },
    {
      "id": "1918108",
      "url": "https://uurl.kbr.be/1918108",
      "pattern": {
        "id": "1918108",
        "hierarchicalPath": [
          {
            "strategy": "direct_digits",
            "path": "1/9/1/8/1/0/8"
          },
          {
            "strategy": "with_prefix",
            "path": "A/1/9/1/8/1/0/8"
          },
          {
            "strategy": "nested_structure",
            "path": "19/18/10/8"
          }
        ],
        "possibleTileStructure": {
          "possibleZoomLevels": {
            "min": 0,
            "max": 10,
            "common": [
              0,
              1,
              2,
              3,
              4,
              5,
              6,
              7,
              8,
              9,
              10
            ],
            "description": "XLimage uses pyramid structure with multiple resolution levels"
          },
          "tileSize": {
            "common": [
              256,
              512,
              1024
            ],
            "default": 256,
            "description": "Most tile systems use 256x256 or 512x512 tiles"
          },
          "fileFormat": {
            "likely": [
              "jpg",
              "jpeg",
              "png"
            ],
            "xlimage_specific": "XLimage may use proprietary format or standard JPEG",
            "quality": "High quality for manuscript viewing"
          },
          "namingConvention": [
            {
              "pattern": "BE-KBR00_A_1918108_0000_00_00_0001.jpg",
              "description": "Standard KBR naming convention"
            },
            {
              "pattern": "{zoom_level}_{tile_x}_{tile_y}.jpg",
              "description": "Common tile naming"
            },
            {
              "pattern": "{id}_{zoom}_{x}_{y}.{format}",
              "description": "ID-based tile naming"
            }
          ]
        }
      }
    }
  ],
  "tileStructure": {},
  "authentication": {},
  "metadata": {},
  "testUrls": [
    "https://uurl.kbr.be/1558106",
    {
      "url": "https://viewerd.kbr.be/gallery.php?map=1/5/5/8/1/0/6/BE-KBR00_A_1558106_0000_00_00_0001.jpg",
      "strategy": "direct_digits"
    },
    {
      "url": "https://viewerd.kbr.be/gallery.php?map=A/1/5/5/8/1/0/6/BE-KBR00_A_1558106_0000_00_00_0001.jpg",
      "strategy": "with_prefix"
    },
    {
      "url": "https://viewerd.kbr.be/gallery.php?map=15/58/10/6/BE-KBR00_A_1558106_0000_00_00_0001.jpg",
      "strategy": "nested_structure"
    },
    {
      "url": "https://viewerd.kbr.be/tiles/1558106/0/0/0.jpg",
      "type": "speculative_tile"
    },
    {
      "url": "https://viewerd.kbr.be/tiles/1558106/0/0/1.jpg",
      "type": "speculative_tile"
    },
    {
      "url": "https://viewerd.kbr.be/tiles/1558106/0/0/2.jpg",
      "type": "speculative_tile"
    },
    {
      "url": "https://viewerd.kbr.be/tiles/1558106/0/1/0.jpg",
      "type": "speculative_tile"
    },
    {
      "url": "https://viewerd.kbr.be/tiles/1558106/0/1/1.jpg",
      "type": "speculative_tile"
    },
    {
      "url": "https://viewerd.kbr.be/tiles/1558106/0/1/2.jpg",
      "type": "speculative_tile"
    },
    {
      "url": "https://viewerd.kbr.be/tiles/1558106/0/2/0.jpg",
      "type": "speculative_tile"
    },
    {
      "url": "https://viewerd.kbr.be/tiles/1558106/0/2/1.jpg",
      "type": "speculative_tile"
    },
    {
      "url": "https://viewerd.kbr.be/tiles/1558106/0/2/2.jpg",
      "type": "speculative_tile"
    },
    {
      "url": "https://viewerd.kbr.be/tiles/1558106/1/0/0.jpg",
      "type": "speculative_tile"
    },
    {
      "url": "https://viewerd.kbr.be/tiles/1558106/1/0/1.jpg",
      "type": "speculative_tile"
    },
    {
      "url": "https://viewerd.kbr.be/tiles/1558106/1/0/2.jpg",
      "type": "speculative_tile"
    },
    {
      "url": "https://viewerd.kbr.be/tiles/1558106/1/1/0.jpg",
      "type": "speculative_tile"
    },
    {
      "url": "https://viewerd.kbr.be/tiles/1558106/1/1/1.jpg",
      "type": "speculative_tile"
    },
    {
      "url": "https://viewerd.kbr.be/tiles/1558106/1/1/2.jpg",
      "type": "speculative_tile"
    },
    {
      "url": "https://viewerd.kbr.be/tiles/1558106/1/2/0.jpg",
      "type": "speculative_tile"
    },
    {
      "url": "https://viewerd.kbr.be/tiles/1558106/1/2/1.jpg",
      "type": "speculative_tile"
    },
    {
      "url": "https://viewerd.kbr.be/tiles/1558106/1/2/2.jpg",
      "type": "speculative_tile"
    },
    {
      "url": "https://viewerd.kbr.be/tiles/1558106/2/0/0.jpg",
      "type": "speculative_tile"
    },
    {
      "url": "https://viewerd.kbr.be/tiles/1558106/2/0/1.jpg",
      "type": "speculative_tile"
    },
    {
      "url": "https://viewerd.kbr.be/tiles/1558106/2/0/2.jpg",
      "type": "speculative_tile"
    },
    {
      "url": "https://viewerd.kbr.be/tiles/1558106/2/1/0.jpg",
      "type": "speculative_tile"
    },
    {
      "url": "https://viewerd.kbr.be/tiles/1558106/2/1/1.jpg",
      "type": "speculative_tile"
    },
    {
      "url": "https://viewerd.kbr.be/tiles/1558106/2/1/2.jpg",
      "type": "speculative_tile"
    },
    {
      "url": "https://viewerd.kbr.be/tiles/1558106/2/2/0.jpg",
      "type": "speculative_tile"
    },
    {
      "url": "https://viewerd.kbr.be/tiles/1558106/2/2/1.jpg",
      "type": "speculative_tile"
    },
    {
      "url": "https://viewerd.kbr.be/tiles/1558106/2/2/2.jpg",
      "type": "speculative_tile"
    },
    {
      "url": "https://viewerd.kbr.be/tiles/1558106/3/0/0.jpg",
      "type": "speculative_tile"
    },
    {
      "url": "https://viewerd.kbr.be/tiles/1558106/3/0/1.jpg",
      "type": "speculative_tile"
    },
    {
      "url": "https://viewerd.kbr.be/tiles/1558106/3/0/2.jpg",
      "type": "speculative_tile"
    },
    {
      "url": "https://viewerd.kbr.be/tiles/1558106/3/1/0.jpg",
      "type": "speculative_tile"
    },
    {
      "url": "https://viewerd.kbr.be/tiles/1558106/3/1/1.jpg",
      "type": "speculative_tile"
    },
    {
      "url": "https://viewerd.kbr.be/tiles/1558106/3/1/2.jpg",
      "type": "speculative_tile"
    },
    {
      "url": "https://viewerd.kbr.be/tiles/1558106/3/2/0.jpg",
      "type": "speculative_tile"
    },
    {
      "url": "https://viewerd.kbr.be/tiles/1558106/3/2/1.jpg",
      "type": "speculative_tile"
    },
    {
      "url": "https://viewerd.kbr.be/tiles/1558106/3/2/2.jpg",
      "type": "speculative_tile"
    }
  ]
}